odoo8_addon_donation_recurring_tax_receipt-8.0.0.1.0.99.dev3-py2.7-nspkg.pth
odoo8_addon_donation_recurring_tax_receipt-8.0.0.1.0.99.dev3.dist-info/METADATA
odoo8_addon_donation_recurring_tax_receipt-8.0.0.1.0.99.dev3.dist-info/RECORD
odoo8_addon_donation_recurring_tax_receipt-8.0.0.1.0.99.dev3.dist-info/WHEEL
odoo8_addon_donation_recurring_tax_receipt-8.0.0.1.0.99.dev3.dist-info/namespace_packages.txt
odoo8_addon_donation_recurring_tax_receipt-8.0.0.1.0.99.dev3.dist-info/top_level.txt
odoo_addons/donation_recurring_tax_receipt/README.rst
odoo_addons/donation_recurring_tax_receipt/__init__.py
odoo_addons/donation_recurring_tax_receipt/__openerp__.py
odoo_addons/donation_recurring_tax_receipt/donation.py
odoo_addons/donation_recurring_tax_receipt/donation_demo.xml
odoo_addons/donation_recurring_tax_receipt/i18n/fr.po
odoo_addons/donation_recurring_tax_receipt/static/description/icon.png
