Metadata-Version: 2.1
Name: odoo8-addon-donation-recurring-tax-receipt
Version: 8.0.0.1.0.99.dev3
Summary: Manage recurring donations with tax receipts
Home-page: http://www.barroux.org
Author: Barroux Abbey, Akretion, Odoo Community Association (OCA)
Author-email: support@odoo-community.org
License: AGPL-3
Platform: UNKNOWN
Classifier: Programming Language :: Python
Classifier: Framework :: Odoo
Classifier: License :: OSI Approved :: GNU Affero General Public License v3
Requires-Python: ~=2.7
Requires-Dist: odoo8-addon-donation-recurring
Requires-Dist: odoo8-addon-donation-tax-receipt
Requires-Dist: odoo (<9.0a,>=8.0a)
